{"version":1,"generatedAt":"2026-02-28T13:24:56.162925551+00:00","deputyId":"PA720370","deputyName":"Ludovic Mendes","groupId":"PO845407","groupLabel":"EPR","totalEntries":4,"authoredCount":4,"cosignedOnlyCount":0,"items":[{"pplId":"DLR5L17N51626","legislature":17,"title":"Convertir des centrales à charbon vers des combustibles moins émetteurs en dioxyde de carbone pour permettre une transition écologique plus juste socialement","isAuthor":true,"isCosigner":false},{"pplId":"DLR5L17N51444","legislature":17,"title":"Pour la répression des occupations illégales et l'amélioration de l'accueil des gens du voyage","isAuthor":true,"isCosigner":false},{"pplId":"DLR5L17N51027","legislature":17,"title":"Pour la valorisation du travail, l’équité salariale et la reconnaissance de l’ancienneté","isAuthor":true,"isCosigner":false},{"pplId":"DLR5L17N52062","legislature":17,"title":"Réglementer les produits de substitution au tabac","isAuthor":true,"isCosigner":false}]}