{"version":1,"generatedAt":"2026-02-27T16:25:40.037800253+00:00","deputyId":"PA795864","deputyName":"Pierre Cazeneuve","groupId":"PO845407","groupLabel":"EPR","totalEntries":2,"authoredCount":2,"cosignedOnlyCount":0,"items":[{"pplId":"DLR5L17N52386","legislature":17,"title":"Décaler progressivement l’âge de départ à la retraite à soixante-cinq ans à l’horizon 2042","isAuthor":true,"isCosigner":false},{"pplId":"DLR5L17N50758","legislature":17,"title":"Interdiction des micro-emballages plastiques destinés à contenir des liquides","isAuthor":true,"isCosigner":false}]}